[{"school":"","banji":"","student":"","backtime":"","applyby":"","applytime":""},{"school":"","banji":"","student":"","backtime":"","applyby":"","applytime":""},{"school":"","banji":"","student":"","backtime":"","applyby":"","applytime":""},{"school":"","banji":"","student":"","backtime":"","applyby":"","applytime":""},{"school":"Williams 深圳外国语 Berczy","banji":"","student":"05 习近平","backtime":"","applyby":"","applytime":"09:33"},{"school":"Williams 深圳外国语 Berczy","banji":"","student":"06 习近平","backtime":"","applyby":"","applytime":"09:33"},{"school":"Williams 深圳外国语 Berczy","banji":"","student":"07 习近平","backtime":"","applyby":"","applytime":"09:33"},{"school":"","banji":"","student":"","backtime":"","applyby":"","applytime":""},{"school":"","banji":"","student":"","backtime":"","applyby":"","applytime":""},{"school":"","banji":"","student":"","backtime":"","applyby":"","applytime":""},{"school":"","banji":"","student":"","backtime":"","applyby":"","applytime":""},{"school":"","banji":"","student":"","backtime":"","applyby":"","applytime":""},{"school":"","banji":"","student":"","backtime":"","applyby":"","applytime":""},{"school":"","banji":"","student":"","backtime":"","applyby":"","applytime":""},{"school":"","banji":"","student":"","backtime":"","applyby":"","applytime":""},{"school":"","banji":"","student":"","backtime":"","applyby":"","applytime":""},{"school":"","banji":"","student":"","backtime":"","applyby":"","applytime":""},{"school":"","banji":"","student":"","backtime":"","applyby":"","applytime":""},{"school":"","banji":"","student":"","backtime":"","applyby":"","applytime":""},{"school":"","banji":"","student":"","backtime":"","applyby":"","applytime":""},{"school":"","banji":"","student":"","backtime":"","applyby":"","applytime":""},{"school":"","banji":"","student":"","backtime":"","applyby":"","applytime":""},{"school":"","banji":"","student":"","backtime":"","applyby":"","applytime":""},{"school":"","banji":"","student":"","backtime":"","applyby":"","applytime":""},{"school":"","banji":"","student":"","backtime":"","applyby":"","applytime":""},{"school":"","banji":"","student":"","backtime":"","applyby":"","applytime":""},{"school":"","banji":"","student":"","backtime":"","applyby":"","applytime":""},{"school":"","banji":"","student":"","backtime":"","applyby":"","applytime":""},{"school":"","banji":"","student":"","backtime":"","applyby":"","applytime":""},{"school":"","banji":"","student":"","backtime":"","applyby":"","applytime":""},{"school":"","banji":"","student":"","backtime":"","applyby":"","applytime":""},{"school":"","banji":"","student":"","backtime":"","applyby":"","applytime":""},{"school":"","banji":"","student":"","backtime":"","applyby":"","applytime":""},{"school":"","banji":"","student":"","backtime":"","applyby":"","applytime":""},{"school":"","banji":"","student":"","backtime":"","applyby":"","applytime":""},{"school":"","banji":"","student":"","backtime":"","applyby":"","applytime":""},{"school":"","banji":"","student":"","backtime":"","applyby":"","applytime":""},{"school":"","banji":"","student":"","backtime":"","applyby":"","applytime":""},{"school":"","banji":"","student":"","backtime":"","applyby":"","applytime":""},{"school":"","banji":"","student":"","backtime":"","applyby":"","applytime":""},{"school":"","banji":"","student":"","backtime":"","applyby":"","applytime":""},{"school":"","banji":"","student":"","backtime":"","applyby":"","applytime":""},{"school":"","banji":"","student":"","backtime":"","applyby":"","applytime":""},{"school":"","banji":"","student":"","backtime":"","applyby":"","applytime":""},{"school":"","banji":"","student":"","backtime":"","applyby":"","applytime":""},{"school":"","banji":"","student":"","backtime":"","applyby":"","applytime":""},{"school":"","banji":"","student":"","backtime":"","applyby":"","applytime":""},{"school":"","banji":"","student":"","backtime":"","applyby":"","applytime":""},{"school":"","banji":"","student":"","backtime":"","applyby":"","applytime":""},{"school":"","banji":"","student":"","backtime":"","applyby":"","applytime":""}]